{"title":"**[STBDA]** 4wk. 미분 / 경사하강법","markdown":{"yaml":{"title":"**[STBDA]** 4wk. 미분 / 경사하강법","author":"JiyunLim","date":"05/14/2023","categories":["빅데이터분석특강"]},"headingText":"강의영상","containsRefs":false,"markdown":"\n\n\n> youtube: https://youtube.com/playlist?list=PLQqh36zP38-xGxAT-3Sq_jpD-eBxpsT8L\n\n### imports\n\n### 미분 \n\n#### tf.GradientTape() 사용방법\n\n`-` 예제9: 카페예제로 돌아오자. \n\n`-` 예제10: 카페예제의 매트릭스 버전 \n\n`-` 이론적인 값을 확인하면 \n\n$loss = ({\\bf y}-{\\bf X \\beta})^\\top ({\\bf y}-{\\bf X \\beta})={\\bf y}^\\top {\\bf y}-{\\bf y^\\top X \\beta} -{\\bf \\beta^\\top X^\\top y} - {\\bf \\beta^\\top X^\\top X \\beta}$\n\n$\\frac{\\partial}{\\partial \\beta} loss = 0 - {\\bf X^\\top y}- {\\bf X^\\top y} + 2{\\bf X^\\top X \\beta}$\n\n$\\hat{\\bf \\beta}=(\\bf X^\\top X)^{-1} X^\\top y$\n\n`-` 예제11: 위의 예제에서 이론적인 $\\boldsymbol{\\beta}$의 최적값을 찾아보고 (즉 $\\boldsymbol{\\hat\\beta}$을 찾고) 그 지점에서 loss의 미분값(=접선의 기울기)를 구하라. 결과가 $\\bf{0}$인지 확인하라. (단 ${\\bf 0}$은 길이가 2이고 각 원소가 0인 벡터)\n\n$\\beta$의 최적값은 $(X'X)^{-1}X'y$이다. \n\n`-` beta_true에서의 기울기도 계산해보자. \n\nloss가 작긴한데 최적보다는 큰데??\n\n- 샘플사이즈가 커진다면 `tape.gradient(loss,beta_true)` $\\approx$ `tape.gradient(loss,beta_optimal)` \n- 샘플사이즈가 커진다면 `beta_true` $\\approx$ `beta_optimal`\n\n## 경사하강법 \n\n### 최적화문제 \n\n`-` $loss=(\\frac{1}{2}\\beta-1)^2$를 최소하는 $\\beta$를 컴퓨터를 활용하여 구하는 문제를 생각해보자. \n- 답은 $\\beta=2$임을 알고 있다. \n\n### 방법1: grid search\n\n#### 알고리즘 \n\n(1) beta = [-10.00,-9.99,...,10.00] 와 같은 리스트를 만든다. \n\n(2) (1)의 리스트의 각원소에 해당하는 loss를 구한다. \n\n(3) (2)에서 구한 loss를 제일 작게 만드는 beta를 찾는다. \n\n#### 구현코드 \n\n#### 그리드서치의 문제점 \n\n`-` 비판1: [-10,10]이외에 해가 존재하면? \n- 이 예제의 경우는 운좋게 [-10,10]에서 해가 존재했음\n- 하지만 임의의 고정된 $x,y$에 대하여 $loss(\\beta)=(x\\beta-y)^2$ 의 형태의 해가 항상 [-10,10]에서 존재한다는 보장은 없음\n- 해결책: 더 넓게 많은 범위를 탐색하자? \n\n`-` 비판2: 효율적이지 않음\n- 알고리즘을 요약하면 결국 -10부터 10까지 작은 간격으로 조금씩 이동하며 loss를 조사하는 것이 grid search의 아이디어 \n- $\\to$ 생각해보니까 $\\beta=2$인 순간 $loss=(\\frac{1}{2}\\beta-1)^2=0$이 되어서 이것보다 작은 최소값은 존재하지 않는다(제곱은 항상 양수이어야 하므로)\n- $\\to$ 따라서 $\\beta=2$ 이후로는 탐색할 필요가 없다 \n\n### 방법2: gradient descent\n\n $loss=(\\frac{1}{2}\\beta-1)^2$\n\n#### 알고리즘!\n\n(1) beta = -5 로 셋팅한다. \n\n(2) beta=-5 근처에서 조금씩 이동하여 loss를 조사해본다. \n\n(3) (2)의 결과를 잘 해석하고 더 유리한 쪽으로 이동 \n\n(4) 위의 과정을 반복하고 왼쪽, 오른쪽 어느쪽으로 움직여도 이득이 없다면 멈춘다. \n\n#### 알고리즘 분석 \n\n`-` (2)-(3)의 과정은 `beta=-5 에서 미분계수를 구하고 미분계수가 양수이면 왼쪽으로 움직이고 음수이면 오른쪽으로 움직인다`고 해석가능. 아래그림을 보면 더 잘 이해가 된다. \n\n#### 왼쪽/오른쪽중에 어디로 갈지 어떻게 판단하는 과정을 수식화?\n\n`-` 아래와 같이 해석가능 \n\n- 오른쪽으로 0.01 간다 = beta_old에 0.01을 더함. (if, 미분계수가 음수) \n- 왼쪽으로 0.01 간다. = beta_old에 0.01을 뺀다. (if, 미분계수가 양수) \n\n`-` 그렇다면 \n$\\beta_{new} = \n\\begin{cases}\n\\beta_{old} + 0.01, & loss'(\\beta_{old})< 0  \\\\ \n\\beta_{old} - 0.01, & loss'(\\beta_{old})> 0 \n\\end{cases}\n$\n\n#### 혹시 알고리즘을 좀 개선할수 있을까?\n\n`-` 항상 0.01씩 움직여야 하는가? \n\n`-` $\\beta=-10$ 일 경우의 접선의 기울기? $\\beta=-4$ 일때 접선의 기울기?\n\n- $\\beta=-10$ => 기울기는 -6 \n- $\\beta=-4$ => 기울기는 -3 \n\n`-` 실제로 6,3씩 이동할순 없으니 적당한 $\\alpha$ (예를들면 $\\alpha=0.01$) 를 잡아서 곱한만큼 이동하자. \n\n`-` 수식화하면 \n\n- $\\beta_{new} = \\beta_{old} - \\alpha~ loss'(\\beta_{old})$ \n- $\\beta_{new} = \\beta_{old} - \\alpha~ \\left[\\frac{\\partial}{\\partial \\beta }loss(\\beta)\\right]_{\\beta=\\beta_{old}}$ \n\n`-` $\\alpha$의 의미\n- $\\alpha$가 크면 크게크게 움직이고 작으면 작게작게 움직인다. \n- $\\alpha>0$ 이어야 한다. \n\n#### 구현코드 \n\n`-` **iter 1**\n\n$\\beta=-10$이라고 하자. \n\n$\\beta = -10$ 에서 0.01만큼 움직이고 싶음 \n\n- 한번 더 움직이자.\n\n`-` **iter2**\n\n- 더 나은 $\\beta$가 되었음! 이렇게 가다보면 $2$까지 잘 갈 수 있을 것 같다!\n\n`-` for 문을 이용하자.  \n\n(강의용) \n\n- 잘 찾았네!\n\n(시도1) beta 다시 초기화 해서 iter 100번 돌려보자.\n\n(시도2) beta 다시 초기화 해서 iter 1000번 돌려보자.\n\n- 10000번 돌렸을 때는 답과 근사했는데 iter 수를 줄였더니 잘 못맞추네... 그럼 이건 알고리즘상 문제가 아니라 보폭이 너무 작아서..느린 것 뿐..\n\n`-` 너무 느린 것 같다? $\\to$ $\\alpha$를 키워보자!\n\n#### 학습률 \n\n`-` 목표: $\\alpha$에 따라서 수렴과정이 어떻게 달라지는 시각화해보자. \n\n##### [시각화 코드 예비학습] \n\n`-` 응용 \n\n예비학습 끝\n\n`-` beta_lst=[-10,-9,-8] 로 이동한다고 하자. \n\n`-` 최종아웃풋 \n\n- beta값과 그에  대응되는 loss값\n\n`-` for \n\n- 너무 느려... 왜 $\\alpha$ 를 바꿔야할지 알듯하다..\n\n### 숙제 \n\n$y=(x-1)^2$를 최소화 하는 $x$를 경사하강법을 이용하여 찾아라. 수렴과정을 animation으로 시각화하라.  \n- x의 초기값은 -3으로 설정한다. \n- 적당한 $\\alpha$를 골라서 100번의 반복안에 수렴하도록 하라. \n","srcMarkdownNoYaml":"\n\n### 강의영상 \n\n> youtube: https://youtube.com/playlist?list=PLQqh36zP38-xGxAT-3Sq_jpD-eBxpsT8L\n\n### imports\n\n### 미분 \n\n#### tf.GradientTape() 사용방법\n\n`-` 예제9: 카페예제로 돌아오자. \n\n`-` 예제10: 카페예제의 매트릭스 버전 \n\n`-` 이론적인 값을 확인하면 \n\n$loss = ({\\bf y}-{\\bf X \\beta})^\\top ({\\bf y}-{\\bf X \\beta})={\\bf y}^\\top {\\bf y}-{\\bf y^\\top X \\beta} -{\\bf \\beta^\\top X^\\top y} - {\\bf \\beta^\\top X^\\top X \\beta}$\n\n$\\frac{\\partial}{\\partial \\beta} loss = 0 - {\\bf X^\\top y}- {\\bf X^\\top y} + 2{\\bf X^\\top X \\beta}$\n\n$\\hat{\\bf \\beta}=(\\bf X^\\top X)^{-1} X^\\top y$\n\n`-` 예제11: 위의 예제에서 이론적인 $\\boldsymbol{\\beta}$의 최적값을 찾아보고 (즉 $\\boldsymbol{\\hat\\beta}$을 찾고) 그 지점에서 loss의 미분값(=접선의 기울기)를 구하라. 결과가 $\\bf{0}$인지 확인하라. (단 ${\\bf 0}$은 길이가 2이고 각 원소가 0인 벡터)\n\n$\\beta$의 최적값은 $(X'X)^{-1}X'y$이다. \n\n`-` beta_true에서의 기울기도 계산해보자. \n\nloss가 작긴한데 최적보다는 큰데??\n\n- 샘플사이즈가 커진다면 `tape.gradient(loss,beta_true)` $\\approx$ `tape.gradient(loss,beta_optimal)` \n- 샘플사이즈가 커진다면 `beta_true` $\\approx$ `beta_optimal`\n\n## 경사하강법 \n\n### 최적화문제 \n\n`-` $loss=(\\frac{1}{2}\\beta-1)^2$를 최소하는 $\\beta$를 컴퓨터를 활용하여 구하는 문제를 생각해보자. \n- 답은 $\\beta=2$임을 알고 있다. \n\n### 방법1: grid search\n\n#### 알고리즘 \n\n(1) beta = [-10.00,-9.99,...,10.00] 와 같은 리스트를 만든다. \n\n(2) (1)의 리스트의 각원소에 해당하는 loss를 구한다. \n\n(3) (2)에서 구한 loss를 제일 작게 만드는 beta를 찾는다. \n\n#### 구현코드 \n\n#### 그리드서치의 문제점 \n\n`-` 비판1: [-10,10]이외에 해가 존재하면? \n- 이 예제의 경우는 운좋게 [-10,10]에서 해가 존재했음\n- 하지만 임의의 고정된 $x,y$에 대하여 $loss(\\beta)=(x\\beta-y)^2$ 의 형태의 해가 항상 [-10,10]에서 존재한다는 보장은 없음\n- 해결책: 더 넓게 많은 범위를 탐색하자? \n\n`-` 비판2: 효율적이지 않음\n- 알고리즘을 요약하면 결국 -10부터 10까지 작은 간격으로 조금씩 이동하며 loss를 조사하는 것이 grid search의 아이디어 \n- $\\to$ 생각해보니까 $\\beta=2$인 순간 $loss=(\\frac{1}{2}\\beta-1)^2=0$이 되어서 이것보다 작은 최소값은 존재하지 않는다(제곱은 항상 양수이어야 하므로)\n- $\\to$ 따라서 $\\beta=2$ 이후로는 탐색할 필요가 없다 \n\n### 방법2: gradient descent\n\n $loss=(\\frac{1}{2}\\beta-1)^2$\n\n#### 알고리즘!\n\n(1) beta = -5 로 셋팅한다. \n\n(2) beta=-5 근처에서 조금씩 이동하여 loss를 조사해본다. \n\n(3) (2)의 결과를 잘 해석하고 더 유리한 쪽으로 이동 \n\n(4) 위의 과정을 반복하고 왼쪽, 오른쪽 어느쪽으로 움직여도 이득이 없다면 멈춘다. \n\n#### 알고리즘 분석 \n\n`-` (2)-(3)의 과정은 `beta=-5 에서 미분계수를 구하고 미분계수가 양수이면 왼쪽으로 움직이고 음수이면 오른쪽으로 움직인다`고 해석가능. 아래그림을 보면 더 잘 이해가 된다. \n\n#### 왼쪽/오른쪽중에 어디로 갈지 어떻게 판단하는 과정을 수식화?\n\n`-` 아래와 같이 해석가능 \n\n- 오른쪽으로 0.01 간다 = beta_old에 0.01을 더함. (if, 미분계수가 음수) \n- 왼쪽으로 0.01 간다. = beta_old에 0.01을 뺀다. (if, 미분계수가 양수) \n\n`-` 그렇다면 \n$\\beta_{new} = \n\\begin{cases}\n\\beta_{old} + 0.01, & loss'(\\beta_{old})< 0  \\\\ \n\\beta_{old} - 0.01, & loss'(\\beta_{old})> 0 \n\\end{cases}\n$\n\n#### 혹시 알고리즘을 좀 개선할수 있을까?\n\n`-` 항상 0.01씩 움직여야 하는가? \n\n`-` $\\beta=-10$ 일 경우의 접선의 기울기? $\\beta=-4$ 일때 접선의 기울기?\n\n- $\\beta=-10$ => 기울기는 -6 \n- $\\beta=-4$ => 기울기는 -3 \n\n`-` 실제로 6,3씩 이동할순 없으니 적당한 $\\alpha$ (예를들면 $\\alpha=0.01$) 를 잡아서 곱한만큼 이동하자. \n\n`-` 수식화하면 \n\n- $\\beta_{new} = \\beta_{old} - \\alpha~ loss'(\\beta_{old})$ \n- $\\beta_{new} = \\beta_{old} - \\alpha~ \\left[\\frac{\\partial}{\\partial \\beta }loss(\\beta)\\right]_{\\beta=\\beta_{old}}$ \n\n`-` $\\alpha$의 의미\n- $\\alpha$가 크면 크게크게 움직이고 작으면 작게작게 움직인다. \n- $\\alpha>0$ 이어야 한다. \n\n#### 구현코드 \n\n`-` **iter 1**\n\n$\\beta=-10$이라고 하자. \n\n$\\beta = -10$ 에서 0.01만큼 움직이고 싶음 \n\n- 한번 더 움직이자.\n\n`-` **iter2**\n\n- 더 나은 $\\beta$가 되었음! 이렇게 가다보면 $2$까지 잘 갈 수 있을 것 같다!\n\n`-` for 문을 이용하자.  \n\n(강의용) \n\n- 잘 찾았네!\n\n(시도1) beta 다시 초기화 해서 iter 100번 돌려보자.\n\n(시도2) beta 다시 초기화 해서 iter 1000번 돌려보자.\n\n- 10000번 돌렸을 때는 답과 근사했는데 iter 수를 줄였더니 잘 못맞추네... 그럼 이건 알고리즘상 문제가 아니라 보폭이 너무 작아서..느린 것 뿐..\n\n`-` 너무 느린 것 같다? $\\to$ $\\alpha$를 키워보자!\n\n#### 학습률 \n\n`-` 목표: $\\alpha$에 따라서 수렴과정이 어떻게 달라지는 시각화해보자. \n\n##### [시각화 코드 예비학습] \n\n`-` 응용 \n\n예비학습 끝\n\n`-` beta_lst=[-10,-9,-8] 로 이동한다고 하자. \n\n`-` 최종아웃풋 \n\n- beta값과 그에  대응되는 loss값\n\n`-` for \n\n- 너무 느려... 왜 $\\alpha$ 를 바꿔야할지 알듯하다..\n\n### 숙제 \n\n$y=(x-1)^2$를 최소화 하는 $x$를 경사하강법을 이용하여 찾아라. 수렴과정을 animation으로 시각화하라.  \n- x의 초기값은 -3으로 설정한다. \n- 적당한 $\\alpha$를 골라서 100번의 반복안에 수렴하도록 하라. \n"},"formats":{"html":{"identifier":{"display-name":"HTML","target-format":"html","base-format":"html"},"execute":{"fig-width":7,"fig-height":5,"fig-format":"retina","fig-dpi":96,"df-print":"default","error":false,"eval":true,"cache":null,"freeze":true,"echo":true,"output":true,"warning":true,"include":true,"keep-md":false,"keep-ipynb":false,"ipynb":null,"enabled":false,"daemon":null,"daemon-restart":false,"debug":false,"ipynb-filters":[],"engine":"jupyter"},"render":{"keep-tex":false,"keep-typ":false,"keep-source":false,"keep-hidden":false,"prefer-html":false,"output-divs":true,"output-ext":"html","fig-align":"default","fig-pos":null,"fig-env":null,"code-fold":false,"code-overflow":"scroll","code-link":false,"code-line-numbers":true,"code-tools":false,"tbl-colwidths":"auto","merge-includes":true,"inline-includes":false,"preserve-yaml":false,"latex-auto-mk":true,"latex-auto-install":true,"latex-clean":true,"latex-max-runs":10,"latex-makeindex":"makeindex","latex-makeindex-opts":[],"latex-tlmgr-opts":[],"latex-input-paths":[],"latex-output-dir":null,"link-external-icon":false,"link-external-newwindow":false,"self-contained-math":false,"format-resources":[],"notebook-links":true},"pandoc":{"standalone":true,"wrap":"none","default-image-extension":"png","to":"html","css":["../../styles.css"],"toc":true,"output-file":"2022_03_28_(4주차)_3월28일.html"},"language":{"toc-title-document":"Table of contents","toc-title-website":"On this page","related-formats-title":"Other Formats","related-notebooks-title":"Notebooks","source-notebooks-prefix":"Source","other-links-title":"Other Links","code-links-title":"Code Links","launch-dev-container-title":"Launch Dev Container","launch-binder-title":"Launch Binder","article-notebook-label":"Article Notebook","notebook-preview-download":"Download Notebook","notebook-preview-download-src":"Download Source","notebook-preview-back":"Back to Article","manuscript-meca-bundle":"MECA Bundle","section-title-abstract":"Abstract","section-title-appendices":"Appendices","section-title-footnotes":"Footnotes","section-title-references":"References","section-title-reuse":"Reuse","section-title-copyright":"Copyright","section-title-citation":"Citation","appendix-attribution-cite-as":"For attribution, please cite this work as:","appendix-attribution-bibtex":"BibTeX citation:","title-block-author-single":"Author","title-block-author-plural":"Authors","title-block-affiliation-single":"Affiliation","title-block-affiliation-plural":"Affiliations","title-block-published":"Published","title-block-modified":"Modified","title-block-keywords":"Keywords","callout-tip-title":"Tip","callout-note-title":"Note","callout-warning-title":"Warning","callout-important-title":"Important","callout-caution-title":"Caution","code-summary":"Code","code-tools-menu-caption":"Code","code-tools-show-all-code":"Show All Code","code-tools-hide-all-code":"Hide All Code","code-tools-view-source":"View Source","code-tools-source-code":"Source Code","code-line":"Line","code-lines":"Lines","copy-button-tooltip":"Copy to Clipboard","copy-button-tooltip-success":"Copied!","repo-action-links-edit":"Edit this page","repo-action-links-source":"View source","repo-action-links-issue":"Report an issue","back-to-top":"Back to top","search-no-results-text":"No results","search-matching-documents-text":"matching documents","search-copy-link-title":"Copy link to search","search-hide-matches-text":"Hide additional matches","search-more-match-text":"more match in this document","search-more-matches-text":"more matches in this document","search-clear-button-title":"Clear","search-detached-cancel-button-title":"Cancel","search-submit-button-title":"Submit","search-label":"Search","toggle-section":"Toggle section","toggle-sidebar":"Toggle sidebar navigation","toggle-dark-mode":"Toggle dark mode","toggle-reader-mode":"Toggle reader mode","toggle-navigation":"Toggle navigation","crossref-fig-title":"Figure","crossref-tbl-title":"Table","crossref-lst-title":"Listing","crossref-thm-title":"Theorem","crossref-lem-title":"Lemma","crossref-cor-title":"Corollary","crossref-prp-title":"Proposition","crossref-cnj-title":"Conjecture","crossref-def-title":"Definition","crossref-exm-title":"Example","crossref-exr-title":"Exercise","crossref-ch-prefix":"Chapter","crossref-apx-prefix":"Appendix","crossref-sec-prefix":"Section","crossref-eq-prefix":"Equation","crossref-lof-title":"List of Figures","crossref-lot-title":"List of Tables","crossref-lol-title":"List of Listings","environment-proof-title":"Proof","environment-remark-title":"Remark","environment-solution-title":"Solution","listing-page-order-by":"Order By","listing-page-order-by-default":"Default","listing-page-order-by-date-asc":"Oldest","listing-page-order-by-date-desc":"Newest","listing-page-order-by-number-desc":"High to Low","listing-page-order-by-number-asc":"Low to High","listing-page-field-date":"Date","listing-page-field-title":"Title","listing-page-field-description":"Description","listing-page-field-author":"Author","listing-page-field-filename":"File Name","listing-page-field-filemodified":"Modified","listing-page-field-subtitle":"Subtitle","listing-page-field-readingtime":"Reading Time","listing-page-field-wordcount":"Word Count","listing-page-field-categories":"Categories","listing-page-minutes-compact":"{0} min","listing-page-category-all":"All","listing-page-no-matches":"No matching items","listing-page-words":"{0} words"},"metadata":{"lang":"en","fig-responsive":true,"quarto-version":"1.4.315","theme":"cosmo","code-copy":true,"title-block-banner":true,"title":"**[STBDA]** 4wk. 미분 / 경사하강법","author":"JiyunLim","date":"05/14/2023","categories":["빅데이터분석특강"]},"extensions":{"book":{"multiFile":true}}}},"projectFormats":["html"]}